Metadata-Version: 2.1
Name: vaby-avb
Version: 0.0.2.post23
Summary: Python implementation of analytic variational Bayesian inference for a nonlinear forward model
Home-page: UNKNOWN
Author: Martin Craig
Author-email: martin.craig@eng.ox.ac.uk
License: Apache-2.0
Platform: UNKNOWN
Classifier: Intended Audience :: Science/Research
Classifier: Programming Language :: Python :: 3
Classifier: Topic :: Scientific/Engineering :: Bio-Informatics
Classifier: License :: OSI Approved :: Apache Software License
License-File: LICENSE
